event_reader.py
event_reader-0.1.10.dist-info/METADATA
event_reader-0.1.10.dist-info/WHEEL
event_reader-0.1.10.dist-info/top_level.txt
event_reader-0.1.10.dist-info/RECORD
