Metadata-Version: 2.1
Name: event_reader
Version: 0.1.10
Summary: A package to read events from a database using SQLAlchemy and Pandas
Author: Ben Lakhoune
Author-email: a.b.lakhoune@gmail.com
Classifier: Development Status :: 3 - Alpha
Classifier: Intended Audience :: Developers
Classifier: License :: OSI Approved :: MIT License
Classifier: Programming Language :: Python :: 3
Classifier: Programming Language :: Python :: 3.6
Classifier: Programming Language :: Python :: 3.7
Classifier: Programming Language :: Python :: 3.8
Requires-Dist: sqlalchemy
Requires-Dist: pandas
Requires-Dist: dogpile.cache
